teacher.py
teacher-0.0.2.dist-info/METADATA
teacher-0.0.2.dist-info/WHEEL
teacher-0.0.2.dist-info/top_level.txt
teacher-0.0.2.dist-info/RECORD
