Metadata-Version: 2.1
Name: teacher
Version: 0.0.2
Summary: attr: teacher.__doc__
Home-page: https://github.com/JulienPalard/teacher
Author: Julien Palard
Author-email: julien@palard.fr
License: MIT License
Keywords: i18n,teaching
Platform: UNKNOWN
Classifier: Development Status :: 1 - Planning
Classifier: Intended Audience :: Developers
Classifier: License :: OSI Approved :: MIT License
Classifier: Programming Language :: Python :: 3.6
Classifier: Programming Language :: Python :: 3.7
Classifier: Programming Language :: Python :: 3.8
Requires-Python: >=3.6
